LICENSE
README.md
setup.py
evently/__init__.py
evently/api.py
evently/utils.py
evently.egg-info/PKG-INFO
evently.egg-info/SOURCES.txt
evently.egg-info/dependency_links.txt
evently.egg-info/top_level.txt
test/__init__.py
test/test_event.py