Metadata-Version: 2.1
Name: evently
Version: 0.1.1
Summary: evently, a lightweight event bus.
Home-page: http://github.com/dboslee/evently/
Author: David Boslee
Author-email: dboslee@gmail.com
License: UNKNOWN
Platform: UNKNOWN
Classifier: Development Status :: 4 - Beta
Classifier: Intended Audience :: Developers
Classifier: License :: OSI Approved :: MIT License
Classifier: Operating System :: OS Independent
Classifier: Programming Language :: Python
Classifier: Programming Language :: Python :: 3.6
Classifier: Programming Language :: Python :: 3.7
Classifier: Programming Language :: Python :: 3.8
License-File: LICENSE
